LICENSE
MANIFEST.in
README.md
requirements.txt
setup.cfg
setup.py
sgmarkets_api_analytics_rates/__init__.py
sgmarkets_api_analytics_rates/__meta__.py
sgmarkets_api_analytics_rates/_obj_from_dict.py
sgmarkets_api_analytics_rates/_util.py
sgmarkets_api_analytics_rates/endpoint.py
sgmarkets_api_analytics_rates/request_curves_custom.py
sgmarkets_api_analytics_rates/request_curves_price.py
sgmarkets_api_analytics_rates/request_swaps_price.py
sgmarkets_api_analytics_rates/response_curves_price.py
sgmarkets_api_analytics_rates/response_swaps_price.py
sgmarkets_api_analytics_rates/slice_curves_price.py
sgmarkets_api_analytics_rates.egg-info/PKG-INFO
sgmarkets_api_analytics_rates.egg-info/SOURCES.txt
sgmarkets_api_analytics_rates.egg-info/dependency_links.txt
sgmarkets_api_analytics_rates.egg-info/not-zip-safe
sgmarkets_api_analytics_rates.egg-info/requires.txt
sgmarkets_api_analytics_rates.egg-info/top_level.txt
sgmarkets_api_analytics_rates/biz/__init__.py
sgmarkets_api_analytics_rates/biz/swap.py
sgmarkets_api_analytics_rates/biz/swap_pricer.py
sgmarkets_api_analytics_rates/markdown/info.md