Metadata-Version: 1.1
Name: sgmarkets-api-analytics-rates
Version: 0.3.0
Summary: sgmarket api analytics RATES helper
Home-page: https://gitlab.com/sgmarkets/sgmarkets-api-analytics-rates
Author: sgmarkets
Author-email: olivier.borderies@gmail.com
License: MIT
Download-URL: https://gitlab.com/sgmarkets/sgmarkets-api-analytics-rates/repository/archive.tar.gz?ref=0.3.0
Keywords: sgmarkets,api,rates
Platform: UNKNOWN
Classifier: Development Status :: 4 - Beta
Classifier: License :: OSI Approved :: MIT License
Classifier: Programming Language :: Python :: 3.5
Classifier: Programming Language :: Python :: 3.6
Classifier: Programming Language :: Python :: 3.7
